[
  {
    "page_num": 1,
    "text": "BCaBA Test Content Outline (6th ed.)\nThe BCaBA Test Content Outline (6th ed.; TCO) describes the content that will appear on the BCaBA® certification examination beginning\nin 2025. The TCO represents the knowledge and skills identified as being important for entry-level BCaBA practitioners by the most recent\njob task analysis (see the February 2022 BACB Newsletter). The BCaBA examination includes 150 scored questions and 25 unscored pilot\nquestions. The TCO includes 90 tasks organized in 9 domains as follows:\nDomain # of Questions (% of Exam)\nA. Behaviorism and Philosophical Foundations 10 (7%)\nB. Concepts and Principles 18 (12%)\nC. Measurement, Data Display, and Interpretation 20 (13%)\nD. Experimental Design 10 (7%)\nE. Ethical and Professional Issues 18 (12%)\nF. Behavior Assessment 17 (11%)\nG. Behavior-Change Procedures 22 (15%)\nH. Intervention Development and Monitoring 20 (13%)\nI. Supervisory Relationships 15 (10%)\nTotal Questions 150\nDomain # of Questions\nA. Behaviorism and Philosophical Foundations\n10\nA.1. Explain the goals of behavior analysis as a natural science A.4. Distinguish among behaviorism, the experimental analysis of\n(i.e., description, prediction, control). behavior, applied behavior analysis, and professional practice\nguided by the science of behavior analysis.\nA.2. Explain the philosophical assumptions underlying the\nscience of behavior analysis (e.g., selectionism, determinism, A.5. Identify and describe dimensions of applied behavior analysis\nempiricism, parsimony, pragmatism). (Baer, Wolf, & Risley, 1968).\nA.3. Describe and explain behavior from the perspective of\nradical behaviorism.\nB. Concepts and Principles\n18\nB.1. Identify and distinguish among behavior, response, and B.8. Identify and distinguish among simple schedules\nresponse class. of reinforcement.\nB.2. Identify and distinguish between stimulus and stimulus class. B.9. Identify examples of operant extinction.\nB.3. Identify and distinguish between respondent and B.10. Identify and distinguish between types of stimulus control.\noperant conditioning.\nB.11. Identify and distinguish between discrimination\nB.4. Identify and distinguish between positive and negative and generalization.\nreinforcement contingencies.\nB.12. Define and identify examples of unconditioned\nB.5. Identify and distinguish between positive and negative motivating operations.\npunishment contingencies.\nB.13. Identify and distinguish between rule-governed and\nB.6. Identify and distinguish between automatic and socially contingency-shaped behavior.\nmediated contingencies.\nB.14. Identify and distinguish among elementary verbal operants.\nB.7. Identify and distinguish among unconditioned, conditioned,\nB.15. Define and identify examples of processes that promote\nand generalized reinforcers and punishers.\nemergent relations and generative performance.\nThis document should be referenced as:\nBehavior Analyst Certification Board. (2022). BCaBA test content outline (6th ed.).\nUpdated 09/2024, Copyright © 2022, BACB® | All rights reserved. https://www.bacb.com/wp-content/bcaba-outline-6thEd/",
    "tables": [
      "| Domain | # of Questions (% of Exam) |\n| --- | --- |\n| A. Behaviorism and Philosophical Foundations | 10 (7%) |\n| B. Concepts and Principles | 18 (12%) |\n| C. Measurement, Data Display, and Interpretation | 20 (13%) |\n| D. Experimental Design | 10 (7%) |\n| E. Ethical and Professional Issues | 18 (12%) |\n| F. Behavior Assessment | 17 (11%) |\n| G. Behavior-Change Procedures | 22 (15%) |\n| H. Intervention Development and Monitoring | 20 (13%) |\n| I. Supervisory Relationships | 15 (10%) |\n| Total Questions | 150 |"
    ]
  },
  {
    "page_num": 2,
    "text": "C. Measurement, Data Display, and Interpretation\n20\nC.1. Define and identify dimensions of behavior (e.g., count, C.6. Evaluate the validity and reliability of measurement procedures.\nduration, magnitude).\nC.7. Select a measurement system to obtain representative\nC.2. Describe the form (i.e., topography) and develop operational data given the dimensions of behavior and the logistics of\ndefinitions of behavior. observing and recording.\nC.3. Distinguish among direct, indirect, and product measures C.8. Graph data to communicate relevant quantitative relations\nof behavior. (e.g., equal-interval graphs, bar graphs, cumulative records).\nC.4. Develop and implement continuous measurement C.9. Interpret graphed data.\nprocedures (e.g., duration recording, event recording).\nC.10. Develop and evaluate mastery criteria.\nC.5. Develop and implement discontinuous measurement\nprocedures (e.g., interval recording, time sampling).\nD. Experimental Design\n10\nD.1. Distinguish between dependent and independent variables. D.5. Distinguish among and implement single-case experimental\ndesigns (e.g., reversal, multiple baseline, multielement,\nD.2. Distinguish between internal and external validity.\nchanging criterion).\nD.3. Identify the defining features of single-case experimental\nD.6. Distinguish among and implement comparative, component,\ndesigns (e.g., individuals serve as their own controls,\nand parametric analyses.\nrepeated measures, prediction, verification, replication).\nD.4. Identify strengths of single-case experimental design.\nE. Ethical and Professional Issues\n18\nE.1. Identify and apply core principles underlying the ethics codes E.6. Identify steps that should be taken when transitioning clients\nfor BACB certificants (e.g., benefit others; treat others with or supervisees to another professional or when a BCaBA\ncompassion, dignity, and respect; behave with integrity). transitions to a different supervisor.\nE.2. Identify the risks to oneself, others, and the profession E.7. Identify types of and risks associated with multiple relationships,\nassociated with engaging in unethical behavior (e.g., misuse and how to mitigate those risks when they are unavoidable.\nof social media, misrepresentation of one’s credential, making\nE.8. Identify and apply interpersonal and other skills (e.g., accepting\nconfidential information public).\nfeedback, listening actively, seeking input, collaborating) to\nE.3. Identify one’s area(s) of competence and when to seek a establish and maintain professional relationships.\nsupervisor’s guidance.\nE.9. Engage in cultural humility in service delivery and\nE.4. Identify professional development activities that strengthen professional relationships.\nand expand areas of competence (e.g., attend conferences,\nE.10. Apply culturally responsive and inclusive service and\nread literature, seek consultation, establish mentors).\nsupervision activities.\nE.5. Identify and comply with requirements for collecting, using,\nE.11. Identify and apply the legal, regulatory, and practice\nprotecting, and disclosing confidential information.\nrequirements (e.g., licensure, jurisprudence, funding, certification)\nrelevant to the delivery of behavior-analytic services.\nF. Behavior Assessment\n17\nF.1. Review relevant information in available records and data F.4. Implement assessments of relevant skill strengths and\n(e.g., educational, medical, historical) at the outset of a case. deficits, and contextual fit (e.g., client values, cultural\nvariables, social validity, environmental resources).\nF.2. Identify conditions that warrant behavior-analytic services.\nF.5. Implement preference and reinforcer assessments.\nF.3. Identify and prioritize socially significant, client-informed, and\nculturally responsive behavior-change goals. F.6. Implement functional assessments of behavior, including\nindirect, descriptive, and experimental analyses.\nUpdated 09/2024, Copyright © 2022, BACB® | All rights reserved. Behavior Analyst Certification Board | BCaBA Test Content Outline (6th ed.) | 2",
    "tables": []
  },
  {
    "page_num": 3,
    "text": "G. Behavior-Change Procedures\n22\nG.1. Develop and implement positive and negative G.11. Develop and implement procedures to promote emergent\nreinforcement procedures, including contingent and relations and generative performance.\nnoncontingent applications.\nG.12. Develop and implement procedures that promote\nG.2. Develop and implement procedures to establish and use behavioral persistence.\nconditioned reinforcers.\nG.13. Develop and implement acquisition procedures that\nG.3. Develop and implement procedures that incorporate are appropriate to the client’s skills and intervention\nmotivating operations and discriminative stimuli. goals (e.g., discrete-trial, free-operant, and naturalistic\nteaching arrangements).\nG.4. Develop and implement procedures to teach simple and\nconditional discriminations. G.14. Develop and implement group contingency procedures.\nG.5. Develop and implement procedures using stimulus and G.15. Develop and implement contingency contracting procedures.\nresponse prompts that include appropriate fading procedures\nG.16. Develop and implement self-management procedures.\n(e.g., errorless, least-to-most, stimulus fading).\nG.17. Develop and implement procedures to promote stimulus and\nG.6. Develop and implement modeling procedures.\nresponse generalization.\nG.7. Develop and implement procedures that use instructions\nG.18. Develop and implement differential reinforcement\nand rules.\nprocedures with and without extinction.\nG.8. Develop and implement shaping procedures.\nG.19. Define and implement positive and negative punishment\nG.9. Develop and implement chaining procedures. procedures (e.g., time-out, response cost, overcorrection).\nG.10. Develop and implement procedures to teach elementary G.20. Develop and implement procedures to promote maintenance\nverbal operants. of behavior change.\nH. Intervention Development and Monitoring\n20\nH.1. State intervention goals in observable and measurable terms. H.5. Identify possible unwanted effects when using reinforcement,\nextinction, and punishment procedures.\nH.2. Identify potential interventions based on assessment results\nand scientific evidence. H.6. Evaluate client progress and procedural integrity.\nH.3. Develop intervention goals and procedures based on risks H.7. Make data-based decisions about the effectiveness of\nand contextual fit (e.g., client preferences and values, cultural procedures and the need for modification.\nvariables, social validity, environmental resources).\nH.8. Collaborate with and include others who support and/or\nH.4. Identify alternative behaviors to be established or increased provide services to clients.\nwhen a target behavior is to be decreased.\nI. Supervisory Relationships\n15\nI.1. Use behavior-analytic supervision practices and state the I.6. Apply empirically validated and competency-based\npotential risks of ineffective supervision (e.g., poor client approaches to train supervisees to perform assessment and\noutcomes, impaired job satisfaction, employee turnover). intervention procedures.\nI.2. Identify and apply strategies for establishing and maintaining I.7. Identify and apply empirically validated and culturally\neffective supervisory relationships (e.g., active listening, responsive performance management procedures (e.g.,\nproviding reinforcement, reciprocal feedback). modeling, practice, feedback, reinforcement, task clarification,\nmanipulation of response effort).\nI.3. Identify and implement methods that promote equity in\nsupervision practices. I.8. Apply a function-based approach (e.g., performance\ndiagnostics) to assess and improve supervisee behavior.\nI.4. Establish clear performance expectations for the supervisor\nand supervisee. I.9. Evaluate the effects of supervision (e.g., on client outcomes,\non supervisee repertoires).\nI.5. Select supervision goals based on an assessment of the\nsupervisee’s skills.\nUpdated 09/2024, Copyright © 2022, BACB® | All rights reserved. Behavior Analyst Certification Board | BCaBA Test Content Outline (6th ed.) | 3",
    "tables": []
  }
]